redpillrush/app/__init__.py
redpillrush/app/bullet.py
redpillrush/app/enemy.py
redpillrush/app/game.py
redpillrush/app/main.py
redpillrush/app/player.py
redpillrush/app/scene.py
redpillrush-0.0.9.dist-info/METADATA
redpillrush-0.0.9.dist-info/WHEEL
redpillrush-0.0.9.dist-info/entry_points.txt
redpillrush-0.0.9.dist-info/top_level.txt
redpillrush-0.0.9.dist-info/RECORD
