Metadata-Version: 2.4
Name: redpillrush
Version: 0.0.9
Summary: A tool for browsing and manipulating CSV files
Author-email: Ryan Gerard Wilson <ryan@wilsonfamilyoffice.com>
License-Expression: MIT
Project-URL: Homepage, https://ryangerardwilson.com
Project-URL: Issues, https://ryangerardwilson.com/contact
Classifier: Programming Language :: Python :: 3
Classifier: Operating System :: OS Independent
Requires-Python: >=3.10
Requires-Dist: raylib
